jadx_mcp_server.py
mseep_jadx_mcp_server-0.1.4.dist-info/licenses/LICENSE
mseep_jadx_mcp_server-0.1.4.dist-info/METADATA
mseep_jadx_mcp_server-0.1.4.dist-info/WHEEL
mseep_jadx_mcp_server-0.1.4.dist-info/entry_points.txt
mseep_jadx_mcp_server-0.1.4.dist-info/top_level.txt
mseep_jadx_mcp_server-0.1.4.dist-info/RECORD
